phenoapt/__init__.py
phenoapt/cli.py
phenoapt/httputil.py
phenoapt/phenoapt.py
phenoapt-0.1.6.dist-info/AUTHORS.rst
phenoapt-0.1.6.dist-info/LICENSE
phenoapt-0.1.6.dist-info/METADATA
phenoapt-0.1.6.dist-info/WHEEL
phenoapt-0.1.6.dist-info/entry_points.txt
phenoapt-0.1.6.dist-info/top_level.txt
phenoapt-0.1.6.dist-info/RECORD
