Metadata-Version: 2.1
Name: phenoapt
Version: 0.1.6
Summary: PhenoApt python client API library
Home-page: https://github.com/phenoapt/phenoapt
Author: PhenoApt Team
Author-email: phenoapt@imperialgene.com
License: MIT license
Keywords: phenoapt
Platform: UNKNOWN
Classifier: Development Status :: 2 - Pre-Alpha
Classifier: Intended Audience :: Developers
Classifier: License :: OSI Approved :: MIT License
Classifier: Natural Language :: English
Classifier: Programming Language :: Python :: 3
Classifier: Programming Language :: Python :: 3.6
Classifier: Programming Language :: Python :: 3.7
Classifier: Programming Language :: Python :: 3.8
Requires-Python: >=3.5
License-File: LICENSE
License-File: AUTHORS.rst
Requires-Dist: Click (>=7.0)
Requires-Dist: requests
Requires-Dist: tabulate
